accesslink/__init__.py
accesslink/accesslink.py
accesslink/oauth2.py
accesslink/endpoints/__init__.py
accesslink/endpoints/daily_activity.py
accesslink/endpoints/daily_activity_transaction.py
accesslink/endpoints/physical_info.py
accesslink/endpoints/physical_info_transaction.py
accesslink/endpoints/pull_notifications.py
accesslink/endpoints/resource.py
accesslink/endpoints/training_data.py
accesslink/endpoints/training_data_transaction.py
accesslink/endpoints/transaction.py
accesslink/endpoints/users.py
polar_accesslink-0.0.5.dist-info/LICENSE
polar_accesslink-0.0.5.dist-info/METADATA
polar_accesslink-0.0.5.dist-info/WHEEL
polar_accesslink-0.0.5.dist-info/top_level.txt
polar_accesslink-0.0.5.dist-info/RECORD
