Metadata-Version: 2.1
Name: polar_accesslink
Version: 0.0.5
Summary: Python wrapper for Polar Open AccessLink API.
Home-page: https://github.com/burnnat/polar_accesslink
Author: Nat Burns
Author-email: nbaccount@burnskids.com
License: MIT license
Keywords: polar_accesslink
Platform: UNKNOWN
Classifier: Development Status :: 2 - Pre-Alpha
Classifier: Intended Audience :: Developers
Classifier: License :: OSI Approved :: MIT License
Classifier: Natural Language :: English
Classifier: Operating System :: OS Independent
Classifier: Topic :: Software Development :: Libraries :: Python Modules
